GaussBinom_distributions_HD/Binomialdistribution.py
GaussBinom_distributions_HD/Gaussiandistribution.py
GaussBinom_distributions_HD/Generaldistribution.py
GaussBinom_distributions_HD/__init__.py
GaussBinom_distributions_HD-1.0.dist-info/METADATA
GaussBinom_distributions_HD-1.0.dist-info/WHEEL
GaussBinom_distributions_HD-1.0.dist-info/top_level.txt
GaussBinom_distributions_HD-1.0.dist-info/RECORD
