Metadata-Version: 2.1
Name: GaussBinom-distributions-HD
Version: 1.0
Summary: Gaussian and Binomial distributions
Home-page: UNKNOWN
Author: Hemanth D
Author-email: hemanthh531@gmail.com
License: UNKNOWN
Platform: UNKNOWN
